<?xml version="1.0"?>
<testResults>
  <FitNesseVersion>v20161106</FitNesseVersion>
  <rootPath>HuntTheWumpus.IterationTwo.StartGame</rootPath>
    <result>
    <counts>
      <right>2</right>
      <wrong>3</wrong>
      <ignores>0</ignores>
      <exceptions>0</exceptions>
    </counts>
    <date>2017-03-23T13:36:01-04:00</date>
    <runTimeInMillis>310</runTimeInMillis>
    <content>&lt;div class="collapsible closed"&gt;&lt;ul&gt;&lt;li&gt;&lt;a href='#' class='expandall'&gt;Expand&lt;/a&gt;&lt;/li&gt;&lt;li&gt;&lt;a href='#' class='collapseall'&gt;Collapse&lt;/a&gt;&lt;/li&gt;&lt;/ul&gt;
	&lt;p class="title"&gt;Included page: &lt;a href="HuntTheWumpus.SetUp"&gt;.HuntTheWumpus.SetUp&lt;/a&gt; &lt;a href="HuntTheWumpus.SetUp?edit&amp;amp;redirectToReferer=true&amp;amp;redirectAction=" class="edit"&gt;(edit)&lt;/a&gt;&lt;/p&gt;
	&lt;div&gt;&lt;table&gt;
	&lt;tr class="slimRowTitle"&gt;
		&lt;td&gt;Import&lt;/td&gt;
	&lt;/tr&gt;
	&lt;tr class="slimRowColor0"&gt;
		&lt;td&gt;&lt;span class="pass"&gt;Fitnesse&lt;/span&gt;&lt;/td&gt;
	&lt;/tr&gt;
&lt;/table&gt;
&lt;br/&gt;&lt;table&gt;
	&lt;tr&gt;
		&lt;td&gt;&lt;span class="pass"&gt;HuntTheWumpusContext&lt;/span&gt;&lt;/td&gt;
	&lt;/tr&gt;
&lt;/table&gt;
&lt;br/&gt;&lt;br/&gt;&lt;/div&gt;
&lt;/div&gt;
&lt;br/&gt;&lt;span class="meta"&gt;variable defined: TEST_SYSTEM=slim&lt;/span&gt;
&lt;br/&gt;&lt;span class="meta"&gt;classpath: ./WumpusGame/bin&lt;/span&gt;&lt;br/&gt;&lt;br/&gt;&lt;table&gt;
	&lt;tr class="slimRowTitle"&gt;
		&lt;td&gt;Import&lt;/td&gt;
	&lt;/tr&gt;
	&lt;tr class="slimRowColor0"&gt;
		&lt;td&gt;&lt;span class="pass"&gt;Fitnesse&lt;/span&gt;&lt;/td&gt;
	&lt;/tr&gt;
&lt;/table&gt;
&lt;br/&gt;Start Game&lt;br/&gt;&lt;br/&gt;Testing the functionality of starting a game&lt;br/&gt;&lt;br/&gt;&lt;table&gt;
	&lt;tr class="slimRowTitle"&gt;
		&lt;td&gt;script&lt;/td&gt;
		&lt;td colspan="2"&gt;&lt;span class="pass"&gt;Start Game&lt;/span&gt;&lt;/td&gt;
	&lt;/tr&gt;
	&lt;tr class="slimRowColor0"&gt;
		&lt;td&gt;check&lt;/td&gt;
		&lt;td&gt;welcomeMessage&lt;/td&gt;
		&lt;td&gt;[welcome&lt;span class="diff"&gt;, press y to continue to the game :)&lt;/span&gt;] &lt;span class="fail"&gt;expected [welcome]&lt;/span&gt;&lt;/td&gt;
	&lt;/tr&gt;
	&lt;tr class="slimRowColor0"&gt;
		&lt;td&gt;check&lt;/td&gt;
		&lt;td&gt;userInputY&lt;/td&gt;
		&lt;td&gt;[&lt;span class="diff"&gt;ente&lt;/span&gt;r&lt;span class="diff"&gt; w a s or d and hit &lt;/span&gt;e&lt;span class="diff"&gt;nter to move&lt;/span&gt;] &lt;span class="fail"&gt;expected [r&lt;/span&gt;&lt;span class="diff"&gt;ul&lt;/span&gt;&lt;span class="fail"&gt;e&lt;/span&gt;&lt;span class="diff"&gt;s&lt;/span&gt;&lt;span class="fail"&gt;]&lt;/span&gt;&lt;/td&gt;
	&lt;/tr&gt;
	&lt;tr class="slimRowColor0"&gt;
		&lt;td&gt;check&lt;/td&gt;
		&lt;td&gt;userInputYEnterGameStart&lt;/td&gt;
		&lt;td&gt;&lt;span class="pass"&gt;true&lt;/span&gt;&lt;/td&gt;
	&lt;/tr&gt;
&lt;/table&gt;
&lt;br/&gt;&lt;br/&gt;&lt;table&gt;
	&lt;tr class="slimRowTitle"&gt;
		&lt;td&gt;script&lt;/td&gt;
		&lt;td colspan="2"&gt;&lt;span class="pass"&gt;Start Game&lt;/span&gt;&lt;/td&gt;
	&lt;/tr&gt;
	&lt;tr class="slimRowColor0"&gt;
		&lt;td&gt;check&lt;/td&gt;
		&lt;td&gt;welcomeMessage&lt;/td&gt;
		&lt;td&gt;[welcome&lt;span class="diff"&gt;, press y to continue to the game :)&lt;/span&gt;] &lt;span class="fail"&gt;expected [welcome]&lt;/span&gt;&lt;/td&gt;
	&lt;/tr&gt;
	&lt;tr class="slimRowColor0"&gt;
		&lt;td&gt;check&lt;/td&gt;
		&lt;td&gt;userInputNGameEnds&lt;/td&gt;
		&lt;td&gt;&lt;span class="pass"&gt;true&lt;/span&gt;&lt;/td&gt;
	&lt;/tr&gt;
&lt;/table&gt;
</content>
    <relativePageName>StartGame</relativePageName>
            <instructions>
            <instructionResult>
        <instruction>{id='import_0_0', instruction='import', path='Fitnesse'}</instruction>
        <slimResult>pass(Fitnesse)</slimResult>
                <expectation>
                    <status>pass</status>
                    <instructionId>import_0_0</instructionId>
                    <col>0</col>
                              <row>1</row>
                    <type>ImportExpectation</type>
                                        <evaluationMessage>Fitnesse</evaluationMessage>
                  </expectation>
              </instructionResult>
            <instructionResult>
        <instruction>{id='decisionTable_1_0', instruction='make', instanceName='decisionTable_1', className='HuntTheWumpusContext', args=[]}</instruction>
        <slimResult>pass(HuntTheWumpusContext)</slimResult>
                <expectation>
                    <status>pass</status>
                    <instructionId>decisionTable_1_0</instructionId>
                    <col>0</col>
                              <row>0</row>
                    <type>ConstructionExpectation</type>
                                        <evaluationMessage>HuntTheWumpusContext</evaluationMessage>
                  </expectation>
              </instructionResult>
            <instructionResult>
        <instruction>{id='import_2_0', instruction='import', path='Fitnesse'}</instruction>
        <slimResult>pass(Fitnesse)</slimResult>
                <expectation>
                    <status>pass</status>
                    <instructionId>import_2_0</instructionId>
                    <col>0</col>
                              <row>1</row>
                    <type>ImportExpectation</type>
                                        <evaluationMessage>Fitnesse</evaluationMessage>
                  </expectation>
              </instructionResult>
            <instructionResult>
        <instruction>{id='scriptTable_3_0', instruction='make', instanceName='scriptTableActor', className='StartGame', args=[]}</instruction>
        <slimResult>pass(Start Game)</slimResult>
                <expectation>
                    <status>pass</status>
                    <instructionId>scriptTable_3_0</instructionId>
                    <col>1</col>
                              <row>0</row>
                    <type>ConstructionExpectation</type>
                                        <evaluationMessage>Start Game</evaluationMessage>
                  </expectation>
              </instructionResult>
            <instructionResult>
        <instruction>{id='scriptTable_3_1', instruction='call', instanceName='scriptTableActor', methodName='welcomeMessage', args=[]}</instruction>
        <slimResult>fail(a=welcome, press y to continue to the game :);e=welcome)</slimResult>
                <expectation>
                    <status>fail</status>
                    <instructionId>scriptTable_3_1</instructionId>
                    <col>2</col>
                              <row>1</row>
                    <type>ReturnedValueExpectation</type>
                    <actual>welcome, press y to continue to the game :)</actual>
                              <expected>welcome</expected>
                            </expectation>
              </instructionResult>
            <instructionResult>
        <instruction>{id='scriptTable_3_2', instruction='call', instanceName='scriptTableActor', methodName='userInputY', args=[]}</instruction>
        <slimResult>fail(a=enter w a s or d and hit enter to move;e=rules)</slimResult>
                <expectation>
                    <status>fail</status>
                    <instructionId>scriptTable_3_2</instructionId>
                    <col>2</col>
                              <row>2</row>
                    <type>ReturnedValueExpectation</type>
                    <actual>enter w a s or d and hit enter to move</actual>
                              <expected>rules</expected>
                            </expectation>
              </instructionResult>
            <instructionResult>
        <instruction>{id='scriptTable_3_3', instruction='call', instanceName='scriptTableActor', methodName='userInputYEnterGameStart', args=[]}</instruction>
        <slimResult>pass(true)</slimResult>
                <expectation>
                    <status>pass</status>
                    <instructionId>scriptTable_3_3</instructionId>
                    <col>2</col>
                              <row>3</row>
                    <type>ReturnedValueExpectation</type>
                                        <evaluationMessage>true</evaluationMessage>
                  </expectation>
              </instructionResult>
            <instructionResult>
        <instruction>{id='scriptTable_4_0', instruction='make', instanceName='scriptTableActor', className='StartGame', args=[]}</instruction>
        <slimResult>pass(Start Game)</slimResult>
                <expectation>
                    <status>pass</status>
                    <instructionId>scriptTable_4_0</instructionId>
                    <col>1</col>
                              <row>0</row>
                    <type>ConstructionExpectation</type>
                                        <evaluationMessage>Start Game</evaluationMessage>
                  </expectation>
              </instructionResult>
            <instructionResult>
        <instruction>{id='scriptTable_4_1', instruction='call', instanceName='scriptTableActor', methodName='welcomeMessage', args=[]}</instruction>
        <slimResult>fail(a=welcome, press y to continue to the game :);e=welcome)</slimResult>
                <expectation>
                    <status>fail</status>
                    <instructionId>scriptTable_4_1</instructionId>
                    <col>2</col>
                              <row>1</row>
                    <type>ReturnedValueExpectation</type>
                    <actual>welcome, press y to continue to the game :)</actual>
                              <expected>welcome</expected>
                            </expectation>
              </instructionResult>
            <instructionResult>
        <instruction>{id='scriptTable_4_2', instruction='call', instanceName='scriptTableActor', methodName='userInputNGameEnds', args=[]}</instruction>
        <slimResult>pass(true)</slimResult>
                <expectation>
                    <status>pass</status>
                    <instructionId>scriptTable_4_2</instructionId>
                    <col>2</col>
                              <row>2</row>
                    <type>ReturnedValueExpectation</type>
                                        <evaluationMessage>true</evaluationMessage>
                  </expectation>
              </instructionResult>
          </instructions>
      </result>
  <executionLog>
    <testSystem>slim:fitnesse.slim.SlimService</testSystem>
    <command>java -cp /Users/Paimon/Downloads/FitNesseRoot/fitnesse-standalone.jar:./WumpusGame/bin fitnesse.slim.SlimService 1</command>
    <exitCode>0</exitCode>
    <stdOut>welcome, press y to continue to the game :)
enter w a s or d and hit enter to move
welcome, press y to continue to the game :)
</stdOut>
    <stdErr></stdErr>
  </executionLog>
  <finalCounts>
    <right>0</right>
    <wrong>1</wrong>
    <ignores>0</ignores>
    <exceptions>0</exceptions>
  </finalCounts>
  <totalRunTimeInMillis>1306</totalRunTimeInMillis>
</testResults>

