<?xml version="1.0"?>
<testResults>
  <FitNesseVersion>v20161106</FitNesseVersion>
  <rootPath>HuntTheWumpus.IterationTwo.PickUpArrow</rootPath>
    <result>
    <counts>
      <right>5</right>
      <wrong>0</wrong>
      <ignores>0</ignores>
      <exceptions>0</exceptions>
    </counts>
    <date>2017-03-23T15:10:05-04:00</date>
    <runTimeInMillis>52</runTimeInMillis>
    <content>&lt;div class="collapsible closed"&gt;&lt;ul&gt;&lt;li&gt;&lt;a href='#' class='expandall'&gt;Expand&lt;/a&gt;&lt;/li&gt;&lt;li&gt;&lt;a href='#' class='collapseall'&gt;Collapse&lt;/a&gt;&lt;/li&gt;&lt;/ul&gt;
	&lt;p class="title"&gt;Included page: &lt;a href="HuntTheWumpus.SetUp"&gt;.HuntTheWumpus.SetUp&lt;/a&gt; &lt;a href="HuntTheWumpus.SetUp?edit&amp;amp;redirectToReferer=true&amp;amp;redirectAction=" class="edit"&gt;(edit)&lt;/a&gt;&lt;/p&gt;
	&lt;div&gt;&lt;table&gt;
	&lt;tr class="slimRowTitle"&gt;
		&lt;td&gt;Import&lt;/td&gt;
	&lt;/tr&gt;
	&lt;tr class="slimRowColor0"&gt;
		&lt;td&gt;&lt;span class="pass"&gt;Fitnesse&lt;/span&gt;&lt;/td&gt;
	&lt;/tr&gt;
&lt;/table&gt;
&lt;br/&gt;&lt;table&gt;
	&lt;tr&gt;
		&lt;td&gt;&lt;span class="pass"&gt;HuntTheWumpusContext&lt;/span&gt;&lt;/td&gt;
	&lt;/tr&gt;
&lt;/table&gt;
&lt;br/&gt;&lt;table&gt;
	&lt;tr&gt;
		&lt;td&gt;&lt;span class="pass"&gt;GenerateMapContext&lt;/span&gt;&lt;/td&gt;
	&lt;/tr&gt;
&lt;/table&gt;
&lt;br/&gt;&lt;/div&gt;
&lt;/div&gt;
&lt;br/&gt;Pick-up Arrow&lt;br/&gt;&lt;br/&gt;Testing the ability to pick-up arrows.&lt;br/&gt;&lt;br/&gt;&lt;span class="meta"&gt;variable defined: TEST_SYSTEM=slim&lt;/span&gt;
&lt;br/&gt;&lt;span class="meta"&gt;classpath: ./WumpusGame/bin&lt;/span&gt;&lt;br/&gt;&lt;br/&gt;Input Map:&lt;br/&gt;&lt;table&gt;
	&lt;tr class="slimRowTitle"&gt;
		&lt;td&gt;script&lt;/td&gt;
		&lt;td colspan="3"&gt;&lt;span class="pass"&gt;Arrow Fixture&lt;/span&gt;&lt;/td&gt;
	&lt;/tr&gt;
	&lt;tr class="slimRowColor4"&gt;
		&lt;td&gt;make&lt;/td&gt;
		&lt;td&gt;Arrow1&lt;/td&gt;
		&lt;td&gt;map&lt;/td&gt;
		&lt;td&gt;E&lt;/td&gt;
	&lt;/tr&gt;
	&lt;tr class="slimRowColor4"&gt;
		&lt;td&gt;make&lt;/td&gt;
		&lt;td&gt;Arrow2&lt;/td&gt;
		&lt;td&gt;map&lt;/td&gt;
		&lt;td&gt;S&lt;/td&gt;
	&lt;/tr&gt;
	&lt;tr class="slimRowColor4"&gt;
		&lt;td&gt;make&lt;/td&gt;
		&lt;td&gt;Empty&lt;/td&gt;
		&lt;td&gt;map&lt;/td&gt;
		&lt;td&gt;W&lt;/td&gt;
	&lt;/tr&gt;
&lt;/table&gt;
&lt;br/&gt;Testing arrow retrival ability:&lt;br/&gt;&lt;table&gt;
	&lt;tr class="slimRowTitle"&gt;
		&lt;td&gt;script&lt;/td&gt;
		&lt;td colspan="2"&gt;&lt;span class="pass"&gt;Pickup Arrow&lt;/span&gt;&lt;/td&gt;
	&lt;/tr&gt;
	&lt;tr class="slimRowColor2"&gt;
		&lt;td colspan="3"&gt;Put User At Location One&lt;/td&gt;
	&lt;/tr&gt;
	&lt;tr class="slimRowColor1"&gt;
		&lt;td colspan="3"&gt;Set Arrow Count To Three&lt;/td&gt;
	&lt;/tr&gt;
	&lt;tr class="slimRowColor0"&gt;
		&lt;td&gt;check&lt;/td&gt;
		&lt;td&gt;getUserArrowCount&lt;/td&gt;
		&lt;td&gt;&lt;span class="pass"&gt;3&lt;/span&gt;&lt;/td&gt;
	&lt;/tr&gt;
	&lt;tr class="slimRowColor0"&gt;
		&lt;td&gt;check&lt;/td&gt;
		&lt;td&gt;Move East&lt;/td&gt;
		&lt;td&gt;&lt;span class="pass"&gt;Congrats, you found one of your arrows.&lt;/span&gt;&lt;/td&gt;
	&lt;/tr&gt;
	&lt;tr class="slimRowColor0"&gt;
		&lt;td&gt;check&lt;/td&gt;
		&lt;td&gt;getUserArrowCount&lt;/td&gt;
		&lt;td&gt;&lt;span class="pass"&gt;4&lt;/span&gt;&lt;/td&gt;
	&lt;/tr&gt;
	&lt;tr class="slimRowColor6"&gt;
		&lt;td colspan="3"&gt;Move East&lt;/td&gt;
	&lt;/tr&gt;
	&lt;tr class="slimRowColor0"&gt;
		&lt;td&gt;check&lt;/td&gt;
		&lt;td&gt;Move South&lt;/td&gt;
		&lt;td&gt;&lt;span class="pass"&gt;Congrats, you found one of your arrows.&lt;/span&gt;&lt;/td&gt;
	&lt;/tr&gt;
	&lt;tr class="slimRowColor0"&gt;
		&lt;td&gt;check&lt;/td&gt;
		&lt;td&gt;getUserArrowCount&lt;/td&gt;
		&lt;td&gt;&lt;span class="pass"&gt;5&lt;/span&gt;&lt;/td&gt;
	&lt;/tr&gt;
&lt;/table&gt;
&lt;br/&gt;</content>
    <relativePageName>PickUpArrow</relativePageName>
            <instructions>
            <instructionResult>
        <instruction>{id='import_0_0', instruction='import', path='Fitnesse'}</instruction>
        <slimResult>pass(Fitnesse)</slimResult>
                <expectation>
                    <status>pass</status>
                    <instructionId>import_0_0</instructionId>
                    <col>0</col>
                              <row>1</row>
                    <type>ImportExpectation</type>
                                        <evaluationMessage>Fitnesse</evaluationMessage>
                  </expectation>
              </instructionResult>
            <instructionResult>
        <instruction>{id='decisionTable_1_0', instruction='make', instanceName='decisionTable_1', className='HuntTheWumpusContext', args=[]}</instruction>
        <slimResult>pass(HuntTheWumpusContext)</slimResult>
                <expectation>
                    <status>pass</status>
                    <instructionId>decisionTable_1_0</instructionId>
                    <col>0</col>
                              <row>0</row>
                    <type>ConstructionExpectation</type>
                                        <evaluationMessage>HuntTheWumpusContext</evaluationMessage>
                  </expectation>
              </instructionResult>
            <instructionResult>
        <instruction>{id='decisionTable_2_0', instruction='make', instanceName='decisionTable_2', className='GenerateMapContext', args=[]}</instruction>
        <slimResult>pass(GenerateMapContext)</slimResult>
                <expectation>
                    <status>pass</status>
                    <instructionId>decisionTable_2_0</instructionId>
                    <col>0</col>
                              <row>0</row>
                    <type>ConstructionExpectation</type>
                                        <evaluationMessage>GenerateMapContext</evaluationMessage>
                  </expectation>
              </instructionResult>
            <instructionResult>
        <instruction>{id='scriptTable_3_0', instruction='make', instanceName='scriptTableActor', className='ArrowFixture', args=[]}</instruction>
        <slimResult>pass(Arrow Fixture)</slimResult>
                <expectation>
                    <status>pass</status>
                    <instructionId>scriptTable_3_0</instructionId>
                    <col>1</col>
                              <row>0</row>
                    <type>ConstructionExpectation</type>
                                        <evaluationMessage>Arrow Fixture</evaluationMessage>
                  </expectation>
              </instructionResult>
            <instructionResult>
        <instruction>{id='scriptTable_3_1', instruction='call', instanceName='scriptTableActor', methodName='makeMap', args=[Arrow1, E]}</instruction>
        <slimResult></slimResult>
                <expectation>
                    <instructionId>scriptTable_3_1</instructionId>
                    <col>0</col>
                              <row>1</row>
                    <type>ScriptActionExpectation</type>
                                      </expectation>
              </instructionResult>
            <instructionResult>
        <instruction>{id='scriptTable_3_2', instruction='call', instanceName='scriptTableActor', methodName='makeMap', args=[Arrow2, S]}</instruction>
        <slimResult></slimResult>
                <expectation>
                    <instructionId>scriptTable_3_2</instructionId>
                    <col>0</col>
                              <row>2</row>
                    <type>ScriptActionExpectation</type>
                                      </expectation>
              </instructionResult>
            <instructionResult>
        <instruction>{id='scriptTable_3_3', instruction='call', instanceName='scriptTableActor', methodName='makeMap', args=[Empty, W]}</instruction>
        <slimResult></slimResult>
                <expectation>
                    <instructionId>scriptTable_3_3</instructionId>
                    <col>0</col>
                              <row>3</row>
                    <type>ScriptActionExpectation</type>
                                      </expectation>
              </instructionResult>
            <instructionResult>
        <instruction>{id='scriptTable_4_0', instruction='make', instanceName='scriptTableActor', className='PickupArrow', args=[]}</instruction>
        <slimResult>pass(Pickup Arrow)</slimResult>
                <expectation>
                    <status>pass</status>
                    <instructionId>scriptTable_4_0</instructionId>
                    <col>1</col>
                              <row>0</row>
                    <type>ConstructionExpectation</type>
                                        <evaluationMessage>Pickup Arrow</evaluationMessage>
                  </expectation>
              </instructionResult>
            <instructionResult>
        <instruction>{id='scriptTable_4_1', instruction='call', instanceName='scriptTableActor', methodName='PutUserAtLocationOne', args=[]}</instruction>
        <slimResult></slimResult>
                <expectation>
                    <instructionId>scriptTable_4_1</instructionId>
                    <col>0</col>
                              <row>1</row>
                    <type>ScriptActionExpectation</type>
                                      </expectation>
              </instructionResult>
            <instructionResult>
        <instruction>{id='scriptTable_4_2', instruction='call', instanceName='scriptTableActor', methodName='SetArrowCountToThree', args=[]}</instruction>
        <slimResult></slimResult>
                <expectation>
                    <instructionId>scriptTable_4_2</instructionId>
                    <col>0</col>
                              <row>2</row>
                    <type>ScriptActionExpectation</type>
                                      </expectation>
              </instructionResult>
            <instructionResult>
        <instruction>{id='scriptTable_4_3', instruction='call', instanceName='scriptTableActor', methodName='getUserArrowCount', args=[]}</instruction>
        <slimResult>pass(3)</slimResult>
                <expectation>
                    <status>pass</status>
                    <instructionId>scriptTable_4_3</instructionId>
                    <col>2</col>
                              <row>3</row>
                    <type>ReturnedValueExpectation</type>
                                        <evaluationMessage>3</evaluationMessage>
                  </expectation>
              </instructionResult>
            <instructionResult>
        <instruction>{id='scriptTable_4_4', instruction='call', instanceName='scriptTableActor', methodName='MoveEast', args=[]}</instruction>
        <slimResult>pass(Congrats, you found one of your arrows.)</slimResult>
                <expectation>
                    <status>pass</status>
                    <instructionId>scriptTable_4_4</instructionId>
                    <col>2</col>
                              <row>4</row>
                    <type>ReturnedValueExpectation</type>
                                        <evaluationMessage>Congrats, you found one of your arrows.</evaluationMessage>
                  </expectation>
              </instructionResult>
            <instructionResult>
        <instruction>{id='scriptTable_4_5', instruction='call', instanceName='scriptTableActor', methodName='getUserArrowCount', args=[]}</instruction>
        <slimResult>pass(4)</slimResult>
                <expectation>
                    <status>pass</status>
                    <instructionId>scriptTable_4_5</instructionId>
                    <col>2</col>
                              <row>5</row>
                    <type>ReturnedValueExpectation</type>
                                        <evaluationMessage>4</evaluationMessage>
                  </expectation>
              </instructionResult>
            <instructionResult>
        <instruction>{id='scriptTable_4_6', instruction='call', instanceName='scriptTableActor', methodName='MoveEast', args=[]}</instruction>
        <slimResult></slimResult>
                <expectation>
                    <instructionId>scriptTable_4_6</instructionId>
                    <col>0</col>
                              <row>6</row>
                    <type>ScriptActionExpectation</type>
                                      </expectation>
              </instructionResult>
            <instructionResult>
        <instruction>{id='scriptTable_4_7', instruction='call', instanceName='scriptTableActor', methodName='MoveSouth', args=[]}</instruction>
        <slimResult>pass(Congrats, you found one of your arrows.)</slimResult>
                <expectation>
                    <status>pass</status>
                    <instructionId>scriptTable_4_7</instructionId>
                    <col>2</col>
                              <row>7</row>
                    <type>ReturnedValueExpectation</type>
                                        <evaluationMessage>Congrats, you found one of your arrows.</evaluationMessage>
                  </expectation>
              </instructionResult>
            <instructionResult>
        <instruction>{id='scriptTable_4_8', instruction='call', instanceName='scriptTableActor', methodName='getUserArrowCount', args=[]}</instruction>
        <slimResult>pass(5)</slimResult>
                <expectation>
                    <status>pass</status>
                    <instructionId>scriptTable_4_8</instructionId>
                    <col>2</col>
                              <row>8</row>
                    <type>ReturnedValueExpectation</type>
                                        <evaluationMessage>5</evaluationMessage>
                  </expectation>
              </instructionResult>
          </instructions>
      </result>
  <executionLog>
    <testSystem></testSystem>
    <command></command>
    <exitCode>0</exitCode>
    <stdOut>welcome
enter y to continue to the game.
rules
enter w, s, a or d to move around. Good Luck :)
50
50
</stdOut>
    <stdErr></stdErr>
  </executionLog>
  <finalCounts>
    <right>1</right>
    <wrong>0</wrong>
    <ignores>0</ignores>
    <exceptions>0</exceptions>
  </finalCounts>
  <totalRunTimeInMillis>52</totalRunTimeInMillis>
</testResults>

